README.md
setup.py
hyper_machines/__init__.py
hyper_machines.egg-info/PKG-INFO
hyper_machines.egg-info/SOURCES.txt
hyper_machines.egg-info/dependency_links.txt
hyper_machines.egg-info/top_level.txt
hyper_machines/edge_machine/EdgeMachine.py
hyper_machines/edge_machine/__init__.py
hyper_machines/state_machine/AbstractStateMachine.py
hyper_machines/state_machine/Edge.py
hyper_machines/state_machine/Node.py
hyper_machines/state_machine/StateMachine.py
hyper_machines/state_machine/__init__.py