Metadata-Version: 2.1
Name: hyper-machines
Version: 0.0.4
Summary: Machines for Python
Home-page: https://github.com/Hypercookie/PythonStateMachine
Author: hypercookie
Author-email: hypercookie@gmx.de
License: MIT
Download-URL: https://github.com/Hypercookie/PythonStateMachine/archive/refs/tags/0.0.4.tar.gz
Platform: UNKNOWN
